{
    "id": 5,
    "sessions": {
        "0": {
            "href": "http://localhost:8080/sessions/0"
        },
        "1": {
            "href": "http://localhost:8080/sessions/1"
        },
        "2": {
            "href": "http://localhost:8080/sessions/2"
        },
        "4": {
            "href": "http://http://localhost:8080/sessions/4"
        }
    },
    "_links": {
        "self": {
            "href": "http://http://localhost:8080/sessions"
        },
        "create": {
            "method": "POST",
            "href": "http://http://localhost:8080/sessions"
        }
    }
}